valentine/__init__.py
valentine/algorithms/__init__.py
valentine/algorithms/base_matcher.py
valentine/algorithms/match.py
valentine/algorithms/matcher_results.py
valentine/algorithms/coma/__init__.py
valentine/algorithms/coma/coma.py
valentine/algorithms/coma/artifact/coma.jar
valentine/algorithms/coma/licenses/README.alignapi.txt
valentine/algorithms/coma/licenses/README.antlr.txt
valentine/algorithms/coma/licenses/README.apache.txt
valentine/algorithms/coma/licenses/README.coma.txt
valentine/algorithms/coma/licenses/README.javolution.txt
valentine/algorithms/coma/licenses/README.jgrapht.txt
valentine/algorithms/coma/licenses/README.junit.txt
valentine/algorithms/coma/licenses/README.matchlibrary.txt
valentine/algorithms/coma/licenses/README.mysql.txt
valentine/algorithms/coma/licenses/README.owlapi.txt
valentine/algorithms/cupid/__init__.py
valentine/algorithms/cupid/cupid_model.py
valentine/algorithms/cupid/linguistic_matching.py
valentine/algorithms/cupid/schema_element.py
valentine/algorithms/cupid/schema_element_node.py
valentine/algorithms/cupid/schema_tree.py
valentine/algorithms/cupid/structural_similarity.py
valentine/algorithms/cupid/tree_match.py
valentine/algorithms/distribution_based/__init__.py
valentine/algorithms/distribution_based/clustering_utils.py
valentine/algorithms/distribution_based/column_model.py
valentine/algorithms/distribution_based/discovery.py
valentine/algorithms/distribution_based/distribution_based.py
valentine/algorithms/distribution_based/emd_utils.py
valentine/algorithms/distribution_based/quantile_histogram.py
valentine/algorithms/jaccard_distance/__init__.py
valentine/algorithms/jaccard_distance/jaccard_distance.py
valentine/algorithms/similarity_flooding/__init__.py
valentine/algorithms/similarity_flooding/graph.py
valentine/algorithms/similarity_flooding/node.py
valentine/algorithms/similarity_flooding/node_pair.py
valentine/algorithms/similarity_flooding/propagation_graph.py
valentine-0.4.1.dist-info/licenses/LICENSE
valentine-0.4.1.dist-info/METADATA
valentine-0.4.1.dist-info/WHEEL
valentine-0.4.1.dist-info/top_level.txt
valentine-0.4.1.dist-info/RECORD
