Metadata-Version: 2.4
Name: valentine
Version: 0.4.1
Summary: Valentine Matcher
Author-email: Delft Data <delftdatasystems@gmail.com>
Maintainer-email: Delft Data <delftdatasystems@gmail.com>
License:                                  Apache License
Project-URL: Homepage, https://delftdata.github.io/valentine/
Project-URL: Documentation, https://delftdata.github.io/valentine/
Project-URL: Source, https://github.com/delftdata/valentine
Project-URL: Issues, https://github.com/delftdata/valentine/issues
Keywords: matching,valentine,schema matching,dataset discovery,coma,cupid,similarity flooding
Classifier: License :: OSI Approved :: Apache Software License
Classifier: Programming Language :: Python :: 3.10
Classifier: Programming Language :: Python :: 3.11
Classifier: Programming Language :: Python :: 3.12
Classifier: Programming Language :: Python :: 3.13
Classifier: Programming Language :: Python :: 3.14
Classifier: Operating System :: POSIX
Classifier: Operating System :: MacOS :: MacOS X
Classifier: Operating System :: Microsoft :: Windows
Requires-Python: <3.15,>=3.10
License-File: LICENSE
Requires-Dist: numpy<3.0,>=2.0
Requires-Dist: pandas<2.4,>=2.0
Requires-Dist: nltk<4.0,>=3.9.1
Requires-Dist: anytree<3.0,>=2.9
Requires-Dist: networkx<4.0,>=2.8
Requires-Dist: chardet<6.0.0,>=5.2.0
Requires-Dist: jellyfish<1.3,>=0.9
Requires-Dist: PuLP<4.0,>=2.5
Requires-Dist: POT<1.0,>=0.9.5
Requires-Dist: python-dateutil<3.0,>=2.8
Dynamic: license-file
